dhydrogen/__init__.py
dhydrogen/classes.py
dhydrogen/errors.py
dhydrogen/hydrogen.py
dhydrogen/types.py
dhydrogen-0.0.0.dist-info/WHEEL
dhydrogen-0.0.0.dist-info/METADATA
dhydrogen-0.0.0.dist-info/RECORD
