Metadata-Version: 2.1
Name: dhydrogen
Version: 0.0.0
Summary: The lighter way to save.
Author: Jase
Author-email: jasew@getdeuterium.win
Requires-Python: >=3.9,<4.0
Classifier: Programming Language :: Python :: 3
Classifier: Programming Language :: Python :: 3.9
